compare_reads-0.0.1.dist-info/WHEEL
compare_reads-0.0.1.dist-info/top_level.txt
compare_reads-0.0.1.dist-info/METADATA
compare_reads-0.0.1.dist-info/RECORD
compare_reads/_compare_reads.pyx
compare_reads/strnum_cmp.c
compare_reads/__init__.py
compare_reads/_compare_reads.c
compare_reads/_compare_reads.so
compare_reads/strnum_cmp.so
compare_reads/_compare_reads.pxd
