Metadata-Version: 2.1
Name: compare-reads
Version: 0.0.1
Summary: cythonized function to compare reads by name
Home-page: https://github.com/mvdbeek/pysam-compare-reads
Author: Marius van den Beek
Author-email: m.vandenbeek@gmail.com
License: MIT license
Project-URL: Documentation, https://pysam-compare-reads.readthedocs.io/
Project-URL: Changelog, https://pysam-compare-reads.readthedocs.io/en/latest/changelog.html
Project-URL: Issue Tracker, https://github.com/mvdbeek/pysam-compare-reads/issues
Platform: UNKNOWN
Classifier: Development Status :: 5 - Production/Stable
Classifier: Intended Audience :: Developers
Classifier: License :: OSI Approved :: MIT License
Classifier: Operating System :: Unix
Classifier: Operating System :: POSIX
Classifier: Operating System :: Microsoft :: Windows
Classifier: Programming Language :: Python
Classifier: Programming Language :: Python :: 2.7
Classifier: Programming Language :: Python :: 3
Classifier: Programming Language :: Python :: 3.4
Classifier: Programming Language :: Python :: 3.5
Classifier: Programming Language :: Python :: 3.6
Classifier: Programming Language :: Python :: 3.7
Classifier: Programming Language :: Python :: Implementation :: CPython
Classifier: Topic :: Utilities
Requires-Python: >=2.7, !=3.0.*, !=3.1.*, !=3.2.*, !=3.3.*
Requires-Dist: pysam
